photoelastimetry/__init__.py
photoelastimetry/disk.py
photoelastimetry/image.py
photoelastimetry/io.py
photoelastimetry/local.py
photoelastimetry/main.py
photoelastimetry/plotting.py
photoelastimetry-0.31.dist-info/licenses/LICENSE
photoelastimetry-0.31.dist-info/METADATA
photoelastimetry-0.31.dist-info/WHEEL
photoelastimetry-0.31.dist-info/entry_points.txt
photoelastimetry-0.31.dist-info/top_level.txt
photoelastimetry-0.31.dist-info/RECORD
